lumino/__init__.py
lumino/api_key.py
lumino/billing.py
lumino/dataset.py
lumino/exceptions.py
lumino/fine_tuning.py
lumino/model.py
lumino/models.py
lumino/sdk.py
lumino/usage.py
lumino/user.py
lumino-0.11.0.dist-info/METADATA
lumino-0.11.0.dist-info/WHEEL
lumino-0.11.0.dist-info/top_level.txt
lumino-0.11.0.dist-info/RECORD
