Metadata-Version: 2.1
Name: lumino
Version: 0.11.0
Summary: A Python SDK for interacting with the Lumino Labs API
Home-page: https://github.com/luminolabs/lumino-sdk-python
Author: Lumino Labs AI
Author-email: engg@luminolabs.ai
License: Apache License 2.0
Requires-Python: >=3.10
Requires-Dist: aiohttp
Requires-Dist: pydantic
Requires-Dist: pydantic[email]
